bmll/LICENSE-2.0.txt
bmll/__init__.py
bmll/_cli.py
bmll/_metadata.json
bmll/_rest.py
bmll/_triggers.py
bmll/_utils.py
bmll/account.py
bmll/apiv2.py
bmll/compute.py
bmll/exceptions.py
bmll/market_data.py
bmll/metadata.py
bmll/reference.py
bmll/time_series.py
bmll/_clusters/__init__.py
bmll/_clusters/components.py
bmll/_clusters/constants.py
bmll/_clusters/core.py
bmll/_clusters/exceptions.py
bmll/_clusters/validation.py
bmll/_core/__init__.py
bmll/_core/collections.py
bmll/_core/enum.py
bmll/_jobs/__init__.py
bmll/_jobs/components.py
bmll/_jobs/core.py
bmll/_jobs/exceptions.py
bmll/_tasks/__init__.py
bmll/_tasks/components.py
bmll/_tasks/core.py
bmll/_tasks/exceptions.py
bmll-1.17.0.dist-info/METADATA
bmll-1.17.0.dist-info/WHEEL
bmll-1.17.0.dist-info/entry_points.txt
bmll-1.17.0.dist-info/top_level.txt
bmll-1.17.0.dist-info/RECORD
